unifed/__init__.py
unifed-0.0.1.dist-info/METADATA
unifed-0.0.1.dist-info/WHEEL
unifed-0.0.1.dist-info/top_level.txt
unifed-0.0.1.dist-info/RECORD
