Metadata-Version: 2.1
Name: unifed
Version: 0.0.1
Summary: unifed
Home-page: https://github.com/AI-secure/FLBenchmark-toolkit
Author: stneng
Author-email: git@stneng.com
License: UNKNOWN
Platform: UNKNOWN
Requires-Python: >=3.6
